MANIFEST.in
RELEASE-VERSION
SConstruct
pavement.py
paver-minilib.zip
setup.py
version.py
demo_rpc/__init__.py
demo_rpc/config.py
demo_rpc/node.py
demo_rpc/Arduino/demo_rpc/Node.cpp
demo_rpc/Arduino/demo_rpc/Node.h
demo_rpc/Arduino/demo_rpc/Node.o
demo_rpc/Arduino/demo_rpc/NodeCommandProcessor.h
demo_rpc/Arduino/demo_rpc/RPCBuffer.h
demo_rpc/Arduino/demo_rpc/RPCBuffer.ht
demo_rpc/Arduino/demo_rpc/SConscript
demo_rpc/Arduino/demo_rpc/config.proto
demo_rpc/Arduino/demo_rpc/demo_rpc.ino
demo_rpc/Arduino/demo_rpc/demo_rpc_config_pb.c
demo_rpc/Arduino/demo_rpc/demo_rpc_config_pb.h
demo_rpc/Arduino/demo_rpc/demo_rpc_config_pb.o
demo_rpc/Arduino/demo_rpc/demo_rpc_config_validate.h
demo_rpc/Arduino/demo_rpc/test.h
demo_rpc/Arduino/demo_rpc/test/SConstruct
demo_rpc/Arduino/demo_rpc/test/main
demo_rpc/Arduino/demo_rpc/test/main.cpp
demo_rpc/Arduino/demo_rpc/test/main.o
demo_rpc/firmware/mega2560/demo_rpc.hex
demo_rpc/firmware/uno/demo_rpc.hex
wheeler.demo_rpc.egg-info/PKG-INFO
wheeler.demo_rpc.egg-info/SOURCES.txt
wheeler.demo_rpc.egg-info/dependency_links.txt
wheeler.demo_rpc.egg-info/requires.txt
wheeler.demo_rpc.egg-info/top_level.txt