Metadata-Version: 1.0
Name: wheeler.demo-rpc
Version: 0.5
Summary: Arduino RPC node packaged as Python package.
Home-page: http://github.com/wheeler-microfluidics/demo_rpc.git
Author: Christian Fobel
Author-email: christian@fobel.net
License: GPLv2
Platform: UNKNOWN
